healthdatalayer/__init__.py
healthdatalayer/config/__init__.py
healthdatalayer/config/config.py
healthdatalayer/config/db.py
healthdatalayer/config/vault.py
healthdatalayer/dtos/__init__.py
healthdatalayer/dtos/collaborator/__init__.py
healthdatalayer/dtos/collaborator/schedule_collaborator.py
healthdatalayer/dtos/medical_visit/__init__.py
healthdatalayer/dtos/medical_visit/medical_certificate.py
healthdatalayer/dtos/medical_visit/recipe_dto.py
healthdatalayer/models/__init__.py
healthdatalayer/models/bridge_area_floor_branch/__init__.py
healthdatalayer/models/bridge_area_floor_branch/area.py
healthdatalayer/models/bridge_area_floor_branch/branch.py
healthdatalayer/models/bridge_area_floor_branch/bridge_area_floor_branch.py
healthdatalayer/models/bridge_area_floor_branch/floor.py
healthdatalayer/models/bridge_area_floor_branch/room.py
healthdatalayer/models/bridge_area_floor_branch/system.py
healthdatalayer/models/client/__init__.py
healthdatalayer/models/client/address.py
healthdatalayer/models/client/city.py
healthdatalayer/models/client/client.py
healthdatalayer/models/client/client_type.py
healthdatalayer/models/client/education.py
healthdatalayer/models/client/emergency_contact.py
healthdatalayer/models/client/gender.py
healthdatalayer/models/client/marriage_status.py
healthdatalayer/models/client/nationality.py
healthdatalayer/models/client/pathological_history.py
healthdatalayer/models/client/pet.py
healthdatalayer/models/client/profession.py
healthdatalayer/models/client/px.py
healthdatalayer/models/client/state.py
healthdatalayer/models/collaborator/__init__.py
healthdatalayer/models/collaborator/collaborator.py
healthdatalayer/models/collaborator/collaborator_speciality.py
healthdatalayer/models/collaborator/collaborator_type.py
healthdatalayer/models/collaborator/schedule.py
healthdatalayer/models/collaborator/speciality.py
healthdatalayer/models/lab/__init__.py
healthdatalayer/models/lab/blood_chemistry_request.py
healthdatalayer-1.7.9.dist-info/METADATA
healthdatalayer-1.7.9.dist-info/WHEEL
healthdatalayer-1.7.9.dist-info/top_level.txt
healthdatalayer-1.7.9.dist-info/RECORD
