Metadata-Version: 2.4
Name: healthdatalayer
Version: 1.7.9
Summary: Health Datalayer to access data from different sources
Author: Jesus Martinez
Author-email: jesusmartinez@noosds.com
Classifier: Programming Language :: Python :: 3.10
Classifier: License :: OSI Approved :: MIT License
Classifier: Operating System :: OS Independent
Requires-Python: >=3.10
Requires-Dist: setuptools
Requires-Dist: wheel
Requires-Dist: twine
Requires-Dist: sqlmodel
Requires-Dist: psycopg2-binary
Requires-Dist: python-dotenv
Requires-Dist: azure-keyvault-secrets
Requires-Dist: azure-identity
Dynamic: author
Dynamic: author-email
Dynamic: classifier
Dynamic: description
Dynamic: description-content-type
Dynamic: requires-dist
Dynamic: requires-python
Dynamic: summary
